ovos_mark1/__init__.py
ovos_mark1/version.py
ovos_mark1/eyes/__init__.py
ovos_mark1/faceplate/__init__.py
ovos_mark1/faceplate/animations.py
ovos_mark1/faceplate/cellular_automaton.py
ovos_mark1/faceplate/icons.py
ovos_mark1_utils-0.0.1.dist-info/LICENSE
ovos_mark1_utils-0.0.1.dist-info/METADATA
ovos_mark1_utils-0.0.1.dist-info/WHEEL
ovos_mark1_utils-0.0.1.dist-info/top_level.txt
ovos_mark1_utils-0.0.1.dist-info/RECORD
