Metadata-Version: 2.1
Name: ovos-mark1-utils
Version: 0.0.1
Summary: UNKNOWN
Home-page: https://github.com/OpenVoiceOS/ovos-mark1-utils
Author: Jarbas
Author-email: jarbas@openvoiceos.com
License: Apache-2.0
Platform: UNKNOWN
Requires-Dist: ovos-bus-client
